angrgdb/__init__.py
angrgdb/commands.py
angrgdb/context_view.py
angrgdb/debugger.py
angrgdb/explore.py
angrgdb-1.0.14.dist-info/DESCRIPTION.rst
angrgdb-1.0.14.dist-info/METADATA
angrgdb-1.0.14.dist-info/RECORD
angrgdb-1.0.14.dist-info/WHEEL
angrgdb-1.0.14.dist-info/metadata.json
angrgdb-1.0.14.dist-info/top_level.txt
