Metadata-Version: 2.0
Name: angrgdb
Version: 1.0.14
Summary: Use angr inside GDB. Create an angr state from the current debugger state. 
Home-page: https://github.com/andreafioraldi/angrgdb
Author: Andrea Fioraldi
Author-email: andreafioraldi@gmail.com
License: BSD 2-Clause
Download-URL: https://github.com/andreafioraldi/angrgdb/archive/1.0.14.tar.gz
Platform: UNKNOWN
Requires-Dist: angrdbg
